datashifts/__init__.py
datashifts/core.py
datashifts-0.8.2.dist-info/.ipynb_checkpoints/PKG-INFO-checkpoint
datashifts-0.8.2.dist-info/.ipynb_checkpoints/SOURCES-checkpoint.txt
datashifts-0.8.2.dist-info/.ipynb_checkpoints/dependency_links-checkpoint.txt
datashifts-0.8.2.dist-info/.ipynb_checkpoints/requires-checkpoint.txt
datashifts-0.8.2.dist-info/.ipynb_checkpoints/top_level-checkpoint.txt
datashifts-0.8.2.dist-info/LICENSE
datashifts-0.8.2.dist-info/METADATA
datashifts-0.8.2.dist-info/WHEEL
datashifts-0.8.2.dist-info/top_level.txt
datashifts-0.8.2.dist-info/RECORD
